dengzhihao/__init__.py
dengzhihao/demo1.py
dengzhihao/demo2.py
dengzhihao-1.0.dist-info/METADATA
dengzhihao-1.0.dist-info/WHEEL
dengzhihao-1.0.dist-info/top_level.txt
dengzhihao-1.0.dist-info/RECORD
