Metadata-Version: 2.1
Name: dengzhihao
Version: 1.0
Summary: 这是第一个对外发布的模块，测试哦
Author: dengzhihao
Author-email: dengzhihao@163.com
